muflon/__init__.py
muflon/io.py
muflon/norms.py
muflon/operations.py
muflon-1.0.3.dist-info/METADATA
muflon-1.0.3.dist-info/WHEEL
muflon-1.0.3.dist-info/top_level.txt
muflon-1.0.3.dist-info/RECORD
