Metadata-Version: 2.4
Name: muflon
Version: 1.0.3
Summary: Library for martice operations
Home-page: https://github.com/Kiryl24/muflon
Author: YJakub Kiryła
Author-email: Jakub Kiryła <kub-kir@wp.pl>
License-Expression: MIT
Project-URL: Homepage, https://github.com/Kiryl24/muflon
Classifier: Programming Language :: Python :: 3
Classifier: Operating System :: OS Independent
Requires-Python: >=3.10
Dynamic: author
Dynamic: home-page
Dynamic: requires-python
